new_timer/__init__.py
new_timer/timer.py
new_timer-0.0.11.dist-info/LICENSE
new_timer-0.0.11.dist-info/METADATA
new_timer-0.0.11.dist-info/WHEEL
new_timer-0.0.11.dist-info/top_level.txt
new_timer-0.0.11.dist-info/RECORD
