Metadata-Version: 2.1
Name: new-timer
Version: 0.0.11
Summary: Program timer.
Home-page: https://github.com/Michael07220823/new_timer.git
Author: Overcomer
Author-email: michael31703@gmail.com
License: MIT License
Keywords: timer
Platform: UNKNOWN
Classifier: Programming Language :: Python :: 3
Classifier: License :: OSI Approved :: MIT License
Classifier: Operating System :: OS Independent
Requires-Python: >=3
License-File: LICENSE
Requires-Dist: numpy
